asyncdagreq/Client.py
asyncdagreq/Errors.py
asyncdagreq/__init__.py
asyncdagreq-1.2.0.dist-info/LICENSE
asyncdagreq-1.2.0.dist-info/METADATA
asyncdagreq-1.2.0.dist-info/WHEEL
asyncdagreq-1.2.0.dist-info/top_level.txt
asyncdagreq-1.2.0.dist-info/RECORD
