Metadata-Version: 2.1
Name: asyncdagreq
Version: 1.2.0
Summary: An async wrapper made in Python for Dagpi.
Home-page: https://github.com/Ali-TM-original/asyncdagreq
Author: Ali-TM-original
Author-email: UNKNOWN
License: MIT
Platform: UNKNOWN
Requires-Dist: aiohttp
